cotarag/__init__.py
cotarag/accelerag/__init__.py
cotarag/accelerag/agentic_utils.py
cotarag/accelerag/arxiv_category_mapper.py
cotarag/accelerag/arxiv_scraper.py
cotarag/accelerag/arxiv_scraping_utils.py
cotarag/accelerag/base_classes.py
cotarag/accelerag/preprocessors.py
cotarag/accelerag/query_utils.py
cotarag/accelerag/cachers/__init__.py
cotarag/accelerag/cachers/caching_utils.py
cotarag/accelerag/cachers/sqlite_cache.py
cotarag/accelerag/embedders/__init__.py
cotarag/accelerag/embedders/image_embedders.py
cotarag/accelerag/embedders/text_embedders.py
cotarag/accelerag/indexers/__init__.py
cotarag/accelerag/indexers/image_indexers.py
cotarag/accelerag/indexers/indexing_utils.py
cotarag/accelerag/indexers/text_indexers.py
cotarag/accelerag/managers/__init__.py
cotarag/accelerag/managers/rag_managers.py
cotarag/accelerag/query_engines/__init__.py
cotarag/accelerag/query_engines/query_engines.py
cotarag/accelerag/retrievers/__init__.py
cotarag/accelerag/retrievers/image_retrievers.py
cotarag/accelerag/retrievers/retriever_utils.py
cotarag/accelerag/retrievers/text_retrievers.py
cotarag/accelerag/scorers/__init__.py
cotarag/accelerag/scorers/scorers.py
cotarag/cota_engine/__init__.py
cotarag/cota_engine/cota_engines.py
cotarag/cota_engine/thought_actions.py
cotarag-0.11.0.dist-info/licenses/LICENSE
cotarag-0.11.0.dist-info/METADATA
cotarag-0.11.0.dist-info/WHEEL
cotarag-0.11.0.dist-info/top_level.txt
cotarag-0.11.0.dist-info/RECORD
