Metadata-Version: 2.4
Name: cotarag
Version: 0.11.0
Summary: Cognitive Thought and Retrieval Augmented Generation - An advanced AI agent framework combining CoTAEngine and AcceleRAG
Author-email: Kernel-Dirichlet <elliottdev93@gmail.com>
License-Expression: AGPL-3.0
Project-URL: Homepage, https://github.com/Kernel-Dirichlet/CoTARAG
Project-URL: Documentation, https://github.com/Kernel-Dirichlet/CoTARAG#readme
Project-URL: Repository, https://github.com/Kernel-Dirichlet/CoTARAG
Project-URL: Issues, https://github.com/Kernel-Dirichlet/CoTARAG/issues
Classifier: Development Status :: 4 - Beta
Classifier: Intended Audience :: Developers
Classifier: Programming Language :: Python :: 3.12
Classifier: Topic :: Scientific/Engineering :: Artificial Intelligence
Classifier: Topic :: Software Development :: Libraries :: Python Modules
Requires-Python: >=3.12
License-File: LICENSE
Requires-Dist: openai>=1.0.0
Requires-Dist: anthropic>=0.8.0
Requires-Dist: arxiv>=2.0.0
Requires-Dist: requests>=2.31.0
Requires-Dist: torch>=2.1.0
Requires-Dist: torchvision>=0.16.0
Requires-Dist: transformers>=4.36.0
Requires-Dist: scikit-learn>=1.3.0
Requires-Dist: Pillow>=10.0.0
Requires-Dist: matplotlib>=3.9.4
Requires-Dist: PyPDF2>=3.0.1
Requires-Dist: numpy>=1.24.0
Requires-Dist: typing-extensions>=4.5.0
Requires-Dist: tqdm>=4.65.0
Provides-Extra: dev
Requires-Dist: pytest>=7.0.0; extra == "dev"
Requires-Dist: pytest-cov>=4.0.0; extra == "dev"
Requires-Dist: black>=23.0.0; extra == "dev"
Requires-Dist: isort>=5.0.0; extra == "dev"
Requires-Dist: mypy>=1.0.0; extra == "dev"
Requires-Dist: ruff>=0.1.0; extra == "dev"
Dynamic: license-file
